MANIFEST.in
setup.py
django_friends.egg-info/PKG-INFO
django_friends.egg-info/SOURCES.txt
django_friends.egg-info/dependency_links.txt
django_friends.egg-info/not-zip-safe
django_friends.egg-info/top_level.txt
friends/__init__.py
friends/admin.py
friends/forms.py
friends/importer.py
friends/management.py
friends/models.py
friends/views.py
friends/templates/notification/friends_accept/full.txt
friends/templates/notification/friends_accept/notice.html
friends/templates/notification/friends_accept_sent/full.txt
friends/templates/notification/friends_accept_sent/notice.html
friends/templates/notification/friends_invite/full.txt
friends/templates/notification/friends_invite/notice.html
friends/templates/notification/friends_invite_sent/full.txt
friends/templates/notification/friends_invite_sent/notice.html
friends/templates/notification/friends_otherconnect/full.txt
friends/templates/notification/friends_otherconnect/notice.html
friends/templates/notification/join_accept/full.txt
friends/templates/notification/join_accept/notice.html